README.rst
setup.py
pySecurityCenter.egg-info/PKG-INFO
pySecurityCenter.egg-info/SOURCES.txt
pySecurityCenter.egg-info/dependency_links.txt
pySecurityCenter.egg-info/requires.txt
pySecurityCenter.egg-info/top_level.txt
securitycenter/__init__.py
securitycenter/base.py
securitycenter/nessus.py
securitycenter/pvs.py
securitycenter/sc4.py
securitycenter/sc5.py