Metadata-Version: 1.1
Name: pySecurityCenter
Version: 3.1.2
Summary: Security Center API Library
Home-page: https://github.com/SteveMcGrath/pySecurityCenter
Author: Steven McGrath <steve@chigeek.com>
Author-email: steve@chigeek.com
License: UNKNOWN
Platform: UNKNOWN
Classifier: Development Status :: 5 - Production/Stable
Classifier: Intended Audience :: Information Technology
Classifier: License :: OSI Approved :: BSD License
Classifier: Natural Language :: English
Classifier: Operating System :: OS Independent
Classifier: Programming Language :: Python :: 2.6
Classifier: Programming Language :: Python :: 2.7
Classifier: Programming Language :: Python :: 3
Classifier: Topic :: Software Development :: Libraries :: Application Frameworks
